indico_livesync/__init__.py
indico_livesync/base.py
indico_livesync/blueprint.py
indico_livesync/cli.py
indico_livesync/controllers.py
indico_livesync/forms.py
indico_livesync/handler.py
indico_livesync/initial.py
indico_livesync/plugin.py
indico_livesync/simplify.py
indico_livesync/task.py
indico_livesync/uploader.py
indico_livesync/util.py
indico_livesync/migrations/20170630_1557_aa0dbc6c14aa_create_tables.py
indico_livesync/migrations/20201023_1224_6ef9616e57cb_add_note_id_and_update_constraints.py
indico_livesync/migrations/20210427_1359_d8e65cb6160d_add_attachment_id_to_queue.py
indico_livesync/migrations/20210506_1917_02a78555cdcb_add_location_changed_change_type.py
indico_livesync/migrations/20210602_1307_330e32d26232_add_undeleted_change_type.py
indico_livesync/migrations/20210608_1713_ff1323696f67_add_published_change_type.py
indico_livesync/models/__init__.py
indico_livesync/models/agents.py
indico_livesync/models/queue.py
indico_livesync/templates/edit_agent.html
indico_livesync/templates/plugin_details_extra.html
indico_livesync/translations/messages.pot
indico_livesync/translations/cs_CZ/LC_MESSAGES/messages.mo
indico_livesync/translations/cs_CZ/LC_MESSAGES/messages.po
indico_livesync/translations/de_DE/LC_MESSAGES/messages.mo
indico_livesync/translations/de_DE/LC_MESSAGES/messages.po
indico_livesync/translations/en_CA/LC_MESSAGES/messages.mo
indico_livesync/translations/en_CA/LC_MESSAGES/messages.po
indico_livesync/translations/en_GB/LC_MESSAGES/messages.mo
indico_livesync/translations/en_GB/LC_MESSAGES/messages.po
indico_livesync/translations/es_ES/LC_MESSAGES/messages.mo
indico_livesync/translations/es_ES/LC_MESSAGES/messages.po
indico_livesync/translations/fr_FR/LC_MESSAGES/messages-js.po
indico_livesync/translations/fr_FR/LC_MESSAGES/messages.mo
indico_livesync/translations/fr_FR/LC_MESSAGES/messages.po
indico_livesync/translations/hu_HU/LC_MESSAGES/messages.mo
indico_livesync/translations/hu_HU/LC_MESSAGES/messages.po
indico_plugin_livesync-3.3.3.dist-info/METADATA
indico_plugin_livesync-3.3.3.dist-info/WHEEL
indico_plugin_livesync-3.3.3.dist-info/entry_points.txt
indico_plugin_livesync-3.3.3.dist-info/RECORD
